ntfy_real_time_client/__init__.py
ntfy_real_time_client/__main__.py
ntfy_real_time_client-0.0.2.dist-info/licenses/LICENSE.txt
ntfy_real_time_client-0.0.2.dist-info/METADATA
ntfy_real_time_client-0.0.2.dist-info/WHEEL
ntfy_real_time_client-0.0.2.dist-info/entry_points.txt
ntfy_real_time_client-0.0.2.dist-info/top_level.txt
ntfy_real_time_client-0.0.2.dist-info/RECORD
