Metadata-Version: 2.4
Name: ntfy-real-time-client
Version: 0.0.2
Summary: Client and framework for receiving notifications via NTFY
Home-page: https://github.com/iacchus/ntfy-real-time-client
Author: Iacchus Mercurius
Author-email: kassivs+git@gmail.com
License: AGPL-3.0-only
Project-URL: Source, https://github.com/iacchus/ntfy-real-time-client
Platform: any
Classifier: Development Status :: 5 - Production/Stable
Classifier: Intended Audience :: Developers
Classifier: Programming Language :: Python
Classifier: Programming Language :: Python :: 3.10
Requires-Python: >=3.10
License-File: LICENSE.txt
Requires-Dist: click
Requires-Dist: requests
Requires-Dist: websocket-client
Provides-Extra: testing
Requires-Dist: setuptools; extra == "testing"
Requires-Dist: pytest; extra == "testing"
Requires-Dist: pytest-cov; extra == "testing"
Dynamic: license-file
